autoskope_client-1.4.0.dist-info/licenses/LICENSE
tests/__init__.py
tests/test_api.py
tests/test_integration.py
tests/test_models.py
autoskope_client-1.4.0.dist-info/METADATA
autoskope_client-1.4.0.dist-info/WHEEL
autoskope_client-1.4.0.dist-info/top_level.txt
autoskope_client-1.4.0.dist-info/RECORD
